aliyunsdkmseap/__init__.py
aliyunsdkmseap/request/__init__.py
aliyunsdkmseap/request/v20210118/ActivateLicenseRequest.py
aliyunsdkmseap/request/v20210118/CallbackTaskRequest.py
aliyunsdkmseap/request/v20210118/DescribeAgreementStatusRequest.py
aliyunsdkmseap/request/v20210118/GenerateUploadFilePolicyForPartnerRequest.py
aliyunsdkmseap/request/v20210118/GetNodeByFlowIdRequest.py
aliyunsdkmseap/request/v20210118/GetNodeByTemplateIdRequest.py
aliyunsdkmseap/request/v20210118/GetPlatformUserInfoForPartnerRequest.py
aliyunsdkmseap/request/v20210118/GetProxyByTypeRequest.py
aliyunsdkmseap/request/v20210118/GetRedisValueRequest.py
aliyunsdkmseap/request/v20210118/GetVariableRequest.py
aliyunsdkmseap/request/v20210118/IdentifyCodeRequest.py
aliyunsdkmseap/request/v20210118/PullRpaModelRequest.py
aliyunsdkmseap/request/v20210118/PullTaskRequest.py
aliyunsdkmseap/request/v20210118/PushRpaTaskDetailRequest.py
aliyunsdkmseap/request/v20210118/PushRpaTaskRequest.py
aliyunsdkmseap/request/v20210118/SendNotificationForPartnerRequest.py
aliyunsdkmseap/request/v20210118/SetRedisValueRequest.py
aliyunsdkmseap/request/v20210118/UpdateAgreementStatusRequest.py
aliyunsdkmseap/request/v20210118/__init__.py
aliyun_python_sdk_mseap-1.0.3.dist-info/LICENSE
aliyun_python_sdk_mseap-1.0.3.dist-info/METADATA
aliyun_python_sdk_mseap-1.0.3.dist-info/WHEEL
aliyun_python_sdk_mseap-1.0.3.dist-info/top_level.txt
aliyun_python_sdk_mseap-1.0.3.dist-info/RECORD
